TrackZero/__init__.py
TrackZero-2.2.2.dist-info/LICENSE
TrackZero-2.2.2.dist-info/METADATA
TrackZero-2.2.2.dist-info/WHEEL
TrackZero-2.2.2.dist-info/top_level.txt
TrackZero-2.2.2.dist-info/RECORD
