Metadata-Version: 2.1
Name: TrackZero
Version: 2.2.2
Summary: TrackZero official Python SDK.
Home-page: https://github.com/leiratech/TrackZero.Python
Author: LEİRA BİLİŞİM TİCARET LİMİTED ŞİRKETİ
Author-email: support@trackzero.io
License: UNKNOWN
Project-URL: Bug Tracker, https://github.com/leiratech/TrackZero.Python/issues
Platform: UNKNOWN
Classifier: Programming Language :: Python :: 3
Classifier: License :: OSI Approved :: MIT License
Classifier: Operating System :: OS Independent
Requires-Python: >=3.6
License-File: LICENSE
